convert_to_queryset/__init__.py
convert_to_queryset/convert.py
convert_to_queryset-0.1.6.dist-info/WHEEL
convert_to_queryset-0.1.6.dist-info/METADATA
convert_to_queryset-0.1.6.dist-info/RECORD
